README
setup.py
django_authopenid/__init__.py
django_authopenid/forms.py
django_authopenid/middleware.py
django_authopenid/mimeparse.py
django_authopenid/models.py
django_authopenid/urls.py
django_authopenid/util.py
django_authopenid/views.py
django_authopenid.egg-info/PKG-INFO
django_authopenid.egg-info/SOURCES.txt
django_authopenid.egg-info/dependency_links.txt
django_authopenid.egg-info/not-zip-safe
django_authopenid.egg-info/top_level.txt
