Metadata-Version: 1.0
Name: django-authopenid
Version: 0.9.6
Summary: Openid authentification application for Django
Home-page: http://code.google.com/p/django-authopenid/
Author: Benoit Chesneau
Author-email: bchesneau@gmail.com
License: BSD
Platform: UNKNOWN
Classifier: Development Status :: 4 - Beta
Classifier: Environment :: Web Environment
Classifier: Intended Audience :: Developers
Classifier: License :: OSI Approved :: BSD License
Classifier: Operating System :: OS Independent
Classifier: Programming Language :: Python
Classifier: Topic :: Internet :: WWW/HTTP
Classifier: Topic :: Utilities
Classifier: Topic :: System :: Systems Administration :: Authentication/Directory
